LICENSE-fr.txt
LICENSE.txt
MANIFEST.in
README.rst
setup.cfg
setup.py
./masai/modelling/pulsar/f90/forpulsar.f90
doc/.DS_Store
doc/Makefile
doc/make.bat
doc/source/.DS_Store
doc/source/changelog.rst
doc/source/citing.rst
doc/source/conf.py
doc/source/develguide.rst
doc/source/faq.rst
doc/source/global.rst
doc/source/index.rst
doc/source/install.rst
doc/source/license.rst
doc/source/userguide.rst
doc/source/_static/Licence_CeCILL-B_V1-fr.html
doc/source/_static/License_CeCILL-B_V1-en.html
doc/source/_static/bg.png
doc/source/_static/header.png
doc/source/_static/masai.css
doc/source/_templates/layout.html
doc/source/api/apihowto.rst
doc/source/api/index.rst
doc/source/api/proc1D_1.rst
doc/source/api/proc1D_2.rst
doc/source/api/examples/__init__.py
doc/source/api/examples/proc1D_1.py
doc/source/api/examples/proc1D_2.py
doc/source/api/images/plot.png
doc/source/apidoc/masai.controllers.rst
doc/source/apidoc/masai.database.rst
doc/source/apidoc/masai.fileio.nmrglue.rst
doc/source/apidoc/masai.fileio.rst
doc/source/apidoc/masai.modelling.pulsar.rst
doc/source/apidoc/masai.modelling.rst
doc/source/apidoc/masai.options.rst
doc/source/apidoc/masai.processing.rst
doc/source/apidoc/masai.rst
doc/source/apidoc/masai.utils.rst
doc/source/apidoc/masai.views.rst
doc/source/apidoc/modules.rst
doc/source/gui/editors.rst_
doc/source/gui/index.rst
doc/source/gui/images/.DS_Store
doc/source/gui/images/mainwindow.png
doc/source/gui/images/opendialog.png
doc/sphinxext/comment_eater.py
doc/sphinxext/compiler_unparse.py
doc/sphinxext/docscrape.py
doc/sphinxext/docscrape.pyc
doc/sphinxext/docscrape_sphinx.py
doc/sphinxext/docscrape_sphinx.pyc
doc/sphinxext/fortran_autodoc.py
doc/sphinxext/fortran_autodoc.pyc
doc/sphinxext/fortran_domain.py
doc/sphinxext/fortran_domain.pyc
doc/sphinxext/inheritance_diagram.py
doc/sphinxext/inheritance_diagram.pyc
doc/sphinxext/ipython_console_highlighting.py
doc/sphinxext/ipython_console_highlighting.pyc
doc/sphinxext/ipython_directive.py
masai.egg-info/PKG-INFO
masai.egg-info/SOURCES.txt
masai.egg-info/dependency_links.txt
masai.egg-info/entry_points.txt
masai.egg-info/namespace_packages.txt
masai.egg-info/top_level.txt
masai.egg-info/zip-safe
