Metadata-Version: 1.1
Name: masai
Version: 0.1.43
Summary: Masai, a framework for processing and modelling of solid state NMR spectra
Home-page: http://fernandezc.github.com/masai
Author: Christian Fernandez
Author-email: christian.fernandez@ensicaen.fr
License: CeCILL-B
Download-URL: http://pypi.python.org/pypi/masai/
Keywords: NMR,Python,Fortran
Platform: UNKNOWN
Classifier: Development Status :: 3 - Alpha
Classifier: Intended Audience :: Science/Research
Classifier: Intended Audience :: Developers
Classifier: Intended Audience :: End Users/Desktop
Classifier: License :: Other/Proprietary License
Classifier: Programming Language :: Python
Classifier: Programming Language :: Fortran
Classifier: Topic :: Scientific/Engineering
Classifier: Operating System :: MacOS :: MacOS X
Classifier: Operating System :: Microsoft :: Windows
Classifier: Operating System :: POSIX :: Linux
Requires: numpy
Requires: scipy
Requires: matplotlib
Requires: traits
